ona/__init__.py
ona/NAR/NARexe
ona/NAR/__init__.py
ona-0.9.2.dist-info/METADATA
ona-0.9.2.dist-info/WHEEL
ona-0.9.2.dist-info/entry_points.txt
ona-0.9.2.dist-info/licenses/LICENSE
ona-0.9.2.dist-info/RECORD
