Metadata-Version: 2.1
Name: ona
Version: 0.9.2
Summary: A wheel for OpenNARS for Applications
Project-URL: Source, https://github.com/ntoxeg/pyona
Project-URL: Sponsor, https://github.com/sponsors/ntoxeg
Project-URL: Tracker, https://github.com/ntoxeg/pyona/issues
Author-email: Adrian Borucki <ab@synthillect.ai>
License-Expression: Apache-2.0
License-File: LICENSE
Keywords: ai,nars
Classifier: Development Status :: 4 - Beta
Classifier: License :: OSI Approved :: Apache Software License
Classifier: Programming Language :: C
Classifier: Programming Language :: Python
Classifier: Programming Language :: Python :: 3.10
Classifier: Programming Language :: Python :: 3.11
Classifier: Programming Language :: Python :: Implementation :: CPython
Requires-Python: >=3.10
